odoo/addons/fieldservice_route/README.rst
odoo/addons/fieldservice_route/__init__.py
odoo/addons/fieldservice_route/__manifest__.py
odoo/addons/fieldservice_route/data/fsm_route_day_data.xml
odoo/addons/fieldservice_route/data/fsm_stage_data.xml
odoo/addons/fieldservice_route/data/ir_sequence.xml
odoo/addons/fieldservice_route/i18n/es_CL.po
odoo/addons/fieldservice_route/i18n/fieldservice_route.pot
odoo/addons/fieldservice_route/i18n/pt_BR.po
odoo/addons/fieldservice_route/i18n/pt_PT.po
odoo/addons/fieldservice_route/migrations/12.0.2.0.0/pre-migration.py
odoo/addons/fieldservice_route/models/__init__.py
odoo/addons/fieldservice_route/models/fsm_location.py
odoo/addons/fieldservice_route/models/fsm_order.py
odoo/addons/fieldservice_route/models/fsm_route.py
odoo/addons/fieldservice_route/models/fsm_route_day.py
odoo/addons/fieldservice_route/models/fsm_route_dayroute.py
odoo/addons/fieldservice_route/models/fsm_stage.py
odoo/addons/fieldservice_route/models/res_partner.py
odoo/addons/fieldservice_route/readme/CONFIGURE.rst
odoo/addons/fieldservice_route/readme/CONTRIBUTORS.rst
odoo/addons/fieldservice_route/readme/CREDITS.rst
odoo/addons/fieldservice_route/readme/DESCRIPTION.rst
odoo/addons/fieldservice_route/readme/USAGE.rst
odoo/addons/fieldservice_route/security/ir.model.access.csv
odoo/addons/fieldservice_route/static/description/icon.png
odoo/addons/fieldservice_route/static/description/index.html
odoo/addons/fieldservice_route/tests/__init__.py
odoo/addons/fieldservice_route/tests/test_fsm_order.py
odoo/addons/fieldservice_route/views/fsm_location.xml
odoo/addons/fieldservice_route/views/fsm_order.xml
odoo/addons/fieldservice_route/views/fsm_route.xml
odoo/addons/fieldservice_route/views/fsm_route_day.xml
odoo/addons/fieldservice_route/views/fsm_route_dayroute.xml
odoo/addons/fieldservice_route/views/menu.xml
odoo/addons/fieldservice_route/views/res_partner_views.xml
odoo12_addon_fieldservice_route-12.0.2.5.0.dist-info/METADATA
odoo12_addon_fieldservice_route-12.0.2.5.0.dist-info/WHEEL
odoo12_addon_fieldservice_route-12.0.2.5.0.dist-info/top_level.txt
odoo12_addon_fieldservice_route-12.0.2.5.0.dist-info/RECORD
